naluconfigs/__init__.py
naluconfigs/_constructors.py
naluconfigs/_version.py
naluconfigs/exceptions.py
naluconfigs/helpers.py
naluconfigs/postprocess.py
naluconfigs/data/chips/aardvarcv3.yml
naluconfigs/data/chips/aardvarcv4.yml
naluconfigs/data/chips/aodsv1.yml
naluconfigs/data/chips/aodsv2.yml
naluconfigs/data/chips/asocv3.yml
naluconfigs/data/chips/hdsocv1.yml
naluconfigs/data/chips/hdsocv2.yml
naluconfigs/data/chips/hiper.yml
naluconfigs/data/chips/udc16.yml
naluconfigs/data/clocks/AODS_300GCC.txt
naluconfigs/data/clocks/AODS_8M.txt
naluconfigs/data/clocks/Si5341-RevD-AARDVARCv2-13GSa_711MGCC-Registers.txt
naluconfigs/data/clocks/Si5341-RevD-AARDVARCv2_GCC781_DebugSE-Registers.txt
naluconfigs/data/clocks/Si5341-RevD-AARDVARCv3_GCC781_DebugSE-Registers.txt
naluconfigs/data/clocks/Si5341-RevD-AARDVARCv4_GCC781_DebugSE-Registers.txt
naluconfigs/data/clocks/Si5341-RevD-ASoC_lambchop-Registers.txt
naluconfigs/data/clocks/Si5341-RevD-HDSoC_15_625SysClk_400GccClk-Registers.txt
naluconfigs/data/clocks/Si5341-RevD-HDSoC_31_25SYSclk_15_625SSTclk_400GCCclk-Registers.txt
naluconfigs/data/clocks/Si5341-RevD-HDSoC_31_25SYSclk_15_625SSTclk_400GccClk_156_25TxClk_31_25TxDivClk-Registers.txt
naluconfigs/data/clocks/Si5341-RevD-HDSoCv1_0035_1Gsaps_FPGA312M-TX312M-SYS31.25M.txt
naluconfigs/data/clocks/Si5341-RevD-HDSoCv2_31_25SYSclk_15_625SSTclk_200GccClk_312_5TxClk_62_5TxDivClk_OUT1-SSTcopy-Registers.txt
naluconfigs/data/clocks/Si5341-RevD-HDSoCv2_31_25SYSclk_15_625SSTclk_200GccClk_312_5TxClk_62_5TxDivClk_OUT2-LVCMOS_OUT1-Registers.txt
naluconfigs/data/clocks/Si5341-RevD-HDSoCv2_31p25-SYSclk_15p625-SSTclk_200-GccClk_312p5-TxClk_62p5-TxDivClk-Registers.txt
naluconfigs/data/clocks/Si5341-RevD-HDSoCv2_31p25-SYSclk_15p625-SSTclk_200-GccClk_312p5-TxClk_62p5-TxDivClk_SSTeast-LVCMOS25-Registers.txt
naluconfigs/data/clocks/Si5341-RevD-HIPeR-NexysFMC_78_125SysClk_312_5GccClk-Registers.txt
naluconfigs/data/clocks/Si5341-RevD-HIPeR_78_125SysClk_312_5GccClk-Registers.txt
naluconfigs-17.7.0.dist-info/METADATA
naluconfigs-17.7.0.dist-info/WHEEL
naluconfigs-17.7.0.dist-info/top_level.txt
naluconfigs-17.7.0.dist-info/RECORD
