Metadata-Version: 2.4
Name: naluconfigs
Version: 17.7.0
Summary: Home for board configs
Home-page: 
Author: Thomas Yang, Emily Lum
Author-email: Marcus Luck <marcus@naluscientific.com>, Mitchell Matsumori-Kelly <mitchell@naluscientific.com>, Alvin Yang <alvin@naluscientific.com>, Kenneth Lauritzen <kenneth@naluscientific.com>, Ben Rotter <ben@naluscientific.com>
Classifier: Development Status :: 3 - Alpha
Classifier: Environment :: Console
Classifier: Programming Language :: Python :: 3
Classifier: Intended Audience :: End Users/Desktop
Classifier: Intended Audience :: Developers
Classifier: License :: OSI Approved :: GNU General Public License v3 (GPLv3)
Classifier: Operating System :: OS Independent
Requires-Python: >=3.7
Requires-Dist: pyyaml>=5.1.1
Requires-Dist: numpy
Provides-Extra: dev
Requires-Dist: pytest; extra == "dev"
Requires-Dist: pytest-mock; extra == "dev"
Requires-Dist: pytest-xdist; extra == "dev"
Requires-Dist: pytest-sugar; extra == "dev"
Dynamic: requires-python
